MANIFEST.in
README.rst
setup.py
docs/HISTORY.txt
docs/LICENSE.GPL
docs/LICENSE.txt
docs/trash.png
ftw/__init__.py
ftw.trash.egg-info/PKG-INFO
ftw.trash.egg-info/SOURCES.txt
ftw.trash.egg-info/dependency_links.txt
ftw.trash.egg-info/entry_points.txt
ftw.trash.egg-info/namespace_packages.txt
ftw.trash.egg-info/not-zip-safe
ftw.trash.egg-info/requires.txt
ftw.trash.egg-info/top_level.txt
ftw/trash/__init__.py
ftw/trash/configure.zcml
ftw/trash/events.py
ftw/trash/exceptions.py
ftw/trash/hooks.py
ftw/trash/indexers.py
ftw/trash/interfaces.py
ftw/trash/lawgiver.zcml
ftw/trash/patches.py
ftw/trash/patches.zcml
ftw/trash/permissions.zcml
ftw/trash/profiles.zcml
ftw/trash/subscribers.py
ftw/trash/testing.py
ftw/trash/trasher.py
ftw/trash/utils.py
ftw/trash/Extensions/__init__.py
ftw/trash/Extensions/install.py
ftw/trash/browser/__init__.py
ftw/trash/browser/configure.zcml
ftw/trash/browser/trash.py
ftw/trash/browser/templates/clean-trash-confirmation.pt
ftw/trash/browser/templates/trash.pt
ftw/trash/locales/ftw.trash.pot
ftw/trash/locales/de/LC_MESSAGES/ftw.trash.po
ftw/trash/profiles/default/actions.xml
ftw/trash/profiles/default/metadata.xml
ftw/trash/profiles/default/rolemap.xml
ftw/trash/profiles/uninstall/actions.xml
ftw/trash/profiles/uninstall/rolemap.xml
ftw/trash/tests/__init__.py
ftw/trash/tests/builders.py
ftw/trash/tests/configure.zcml
ftw/trash/tests/dexterity_folder.py
ftw/trash/tests/test_catalog.py
ftw/trash/tests/test_deletion.py
ftw/trash/tests/test_installation.py
ftw/trash/tests/test_plone.py
ftw/trash/tests/test_ploneformgen.py
ftw/trash/tests/test_profiles.py
ftw/trash/tests/test_trash_view.py
ftw/trash/tests/test_trasher.py
ftw/trash/tests/test_traversing.py
ftw/trash/tests/test_uninstall.py
ftw/trash/tests/test_utils.py
ftw/trash/tests/test_zmi.py
ftw/trash/tests/profiles/dxtests/types.xml
ftw/trash/tests/profiles/dxtests/types/dxfolder.xml
ftw/trash/upgrades/__init__.py
ftw/trash/upgrades/20180713212445_add__clean_trash__permission/__init__.py
ftw/trash/upgrades/20180713212445_add__clean_trash__permission/rolemap.xml
ftw/trash/upgrades/20180713212445_add__clean_trash__permission/upgrade.py
ftw/trash/upgrades/20191209083900_fix_trash_action_name/__init__.py
