Metadata-Version: 2.1
Name: ftw.trash
Version: 1.7.2
Summary: A Plone addon introducing a trash with restore functionality.
Home-page: https://github.com/4teamwork/ftw.trash
Author: 4teamwork AG
Author-email: mailto:info@4teamwork.ch
License: GPL2
Keywords: ftw trash
Platform: UNKNOWN
Classifier: Framework :: Plone
Classifier: Framework :: Plone :: 4.3
Classifier: Framework :: Plone :: 5.1
Classifier: License :: OSI Approved :: GNU General Public License (GPL)
Classifier: Programming Language :: Python
Classifier: Programming Language :: Python :: 2.7
Classifier: Topic :: Software Development :: Libraries :: Python Modules
Provides-Extra: tests
